sonata/__init__.py
sonata/constants.py
sonata/core/__init__.py
sonata/core/asr.py
sonata/core/audio_event_detector.py
sonata/core/speaker_diarization.py
sonata/core/transcriber.py
sonata/libs/__init__.py
sonata/main.py
sonata/models/__init__.py
sonata/models/asr.py
sonata/models/emotive.py
sonata/models/model_loader.py
sonata/models/whisperx.py
sonata/utils/__init__.py
sonata/utils/audio.py
sonata/utils/audio_converter.py
sonata_asr-0.1.1.dist-info/LICENSE
sonata_asr-0.1.1.dist-info/METADATA
sonata_asr-0.1.1.dist-info/WHEEL
sonata_asr-0.1.1.dist-info/entry_points.txt
sonata_asr-0.1.1.dist-info/RECORD
