Metadata-Version: 2.3
Name: sonata-asr
Version: 0.1.1
Summary: SONATA: SOund and Narrative Advanced Transcription Assistant
License: GPL-3.0-or-later
Keywords: sonata,sonata-asr,audio,transcription,speech,emotion,ASR,whisper,audio-detection,sound-events,speaker-diarization,audio-analysis,non-verbal-cues,emotive-sounds,multilingual,speech-recognition,speech-to-text,audio-classification,audio-events,audio-processing,voice-analysis,language-detection,whisperx,automatic-speech-recognition,voice-transcription,speaker-recognition,multimodal,audio-segmentation,audio-preprocessing,word-timestamps,emotion-detection,noise-detection,multi-speaker,subtit
Author: hwk06023
Author-email: hwk06023@github.com
Requires-Python: >=3.8,<4.0
Classifier: Intended Audience :: Developers
Classifier: Intended Audience :: Science/Research
Classifier: License :: OSI Approved :: GNU General Public License v3 or later (GPLv3+)
Classifier: Operating System :: OS Independent
Classifier: Programming Language :: Python :: 3
Classifier: Programming Language :: Python :: 3.8
Classifier: Programming Language :: Python :: 3.9
Classifier: Programming Language :: Python :: 3.10
Classifier: Programming Language :: Python :: 3.11
Classifier: Programming Language :: Python :: 3.12
Classifier: Programming Language :: Python :: 3.13
Classifier: Topic :: Multimedia :: Sound/Audio :: Speech
Classifier: Topic :: Scientific/Engineering :: Artificial Intelligence
Requires-Dist: huggingface_hub (>=0.12.0)
Requires-Dist: librosa (>=0.10.0)
Requires-Dist: matplotlib (>=3.5.0)
Requires-Dist: networkx (>=2.6.3)
Requires-Dist: numpy (>=1.20.0)
Requires-Dist: pyannote.audio (>=2.1.1)
Requires-Dist: pyannote.core (>=4.5)
Requires-Dist: pyannote.metrics (>=3.2)
Requires-Dist: pyannote.pipeline (>=2.3)
Requires-Dist: pydub (>=0.25.1)
Requires-Dist: scikit-learn (>=1.0.0)
Requires-Dist: scipy (>=1.7.0)
Requires-Dist: soundfile (>=0.10.3)
Requires-Dist: speechbrain (>=0.5.14)
Requires-Dist: torch (>=1.10.0)
Requires-Dist: torchaudio (>=2.0.0)
Requires-Dist: tqdm (>=4.62.0)
Requires-Dist: transformers (>=4.30.0)
Requires-Dist: webrtcvad-wheels (>=2.0.11)
Requires-Dist: whisperx (>=3.1.0)
Project-URL: Bug Tracker, https://github.com/hwk06023/SONATA/issues
Project-URL: Documentation, https://github.com/hwk06023/SONATA
Project-URL: Repository, https://github.com/hwk06023/SONATA
